senvx/__init__.py
senvx/common.py
senvx/constants.py
senvx/errors.py
senvx/install.py
senvx/main.py
senvx/models.py
senvx/tests/__init__.py
senvx/tests/conftest.py
senvx/tests/integration/__init__.py
senvx/tests/integration/test_install.py
senvx/tests/static/black-corrupted.lock.json
senvx/tests/static/black-standard-conda-lock
senvx/tests/static/black-with-meta.lock.json
senvx/tests/static/black-with-no-name.lock.json
senvx/tests/unit/__init__.py
senvx/tests/unit/test_install.py
senvx-0.0.2.dist-info/entry_points.txt
senvx-0.0.2.dist-info/LICENSE
senvx-0.0.2.dist-info/WHEEL
senvx-0.0.2.dist-info/METADATA
senvx-0.0.2.dist-info/RECORD
